{"id":"2AJc","dependencies":[{"name":"/Users/Wyj/Workspace/52admln.github.io/package.json","includedInParent":true,"mtime":1533011431322}],"generated":{"js":"module.exports=\"/04eecf6e4fe9ff38ab6b9861dd3e9fe1.ttf\";","map":{"mappings":[{"source":"0","name":"module","original":{"line":1,"column":0},"generated":{"line":1,"column":0}},{"source":"0","name":"exports","original":{"line":1,"column":7},"generated":{"line":1,"column":7}},{"source":"0","original":{"line":1,"column":17},"generated":{"line":1,"column":15}}],"sources":{},"lineCount":null}},"hash":"7885dc2714bfd3d5b67a87e23e8028ba","cacheData":{"env":{}}}