{"id":"style/index.scss","dependencies":[{"name":"/Users/Wyj/Workspace/52admln.github.io/package.json","includedInParent":true,"mtime":1533011431322},{"name":"./fonts/Source_Sans_Pro/SourceSansPro-Regular.ttf","dynamic":true,"parent":"/Users/Wyj/Workspace/52admln.github.io/src/style/index.scss","resolved":"/Users/Wyj/Workspace/52admln.github.io/src/style/fonts/Source_Sans_Pro/SourceSansPro-Regular.ttf"},{"name":"./fonts/Source_Sans_Pro/SourceSansPro-Light.ttf","dynamic":true,"parent":"/Users/Wyj/Workspace/52admln.github.io/src/style/index.scss","resolved":"/Users/Wyj/Workspace/52admln.github.io/src/style/fonts/Source_Sans_Pro/SourceSansPro-Light.ttf"},{"name":"./fonts/Source_Sans_Pro/SourceSansPro-Semibold.ttf","dynamic":true,"parent":"/Users/Wyj/Workspace/52admln.github.io/src/style/index.scss","resolved":"/Users/Wyj/Workspace/52admln.github.io/src/style/fonts/Source_Sans_Pro/SourceSansPro-Semibold.ttf"},{"name":"./fonts/Dosis/Dosis-Medium.ttf","dynamic":true,"parent":"/Users/Wyj/Workspace/52admln.github.io/src/style/index.scss","resolved":"/Users/Wyj/Workspace/52admln.github.io/src/style/fonts/Dosis/Dosis-Medium.ttf"},{"name":"/Users/Wyj/Workspace/52admln.github.io/.postcssrc","includedInParent":true,"mtime":1533015130375},{"name":"_css_loader","parent":"/Users/Wyj/Workspace/52admln.github.io/src/style/index.scss","resolved":"/usr/local/share/.config/yarn/global/node_modules/parcel-bundler/src/builtins/css-loader.js"}],"generated":{"css":"@font-face {\n  font-family: \"Source Sans Pro\";\n  src: local(\"Source Sans Pro\"), url(\"bc170c7c687669c8f711d611501601df.ttf\"); }\n\n@font-face {\n  font-family: \"Source Sans Pro\";\n  src: local(\"Source Sans Pro Light\"), url(\"c0472aa68c9f06ebae9c6b332ef61b60.ttf\");\n  font-weight: 300; }\n\n@font-face {\n  font-family: \"Source Sans Pro\";\n  src: local(\"Source Sans Pro Semibold\"), url(\"f8bdef0d6ce786d57a32f79cb0b40f38.ttf\");\n  font-weight: 600; }\n\n@font-face {\n  font-family: \"Dosis\";\n  src: local(\"Dosis Medium\"), url(\"04eecf6e4fe9ff38ab6b9861dd3e9fe1.ttf\");\n  font-weight: 500; }\n\nhtml, body, div, h2, h4, span, i, a {\n  margin: 0;\n  padding: 0; }\n\nbody {\n  font-family: \"Source Sans Pro\", \"Helvetica Neue\", Arial, sans-serif;\n  -webkit-font-smoothing: antialiased;\n  -moz-osx-font-smoothing: grayscale;\n  overflow: hidden; }\n\na {\n  text-decoration: none; }\n\nbody::before {\n  content: '';\n  position: absolute;\n  top: 20%;\n  left: 40%;\n  width: 360px;\n  height: 360px;\n  border-radius: 50%;\n  background-image: -webkit-gradient(linear, left bottom, left top, from(#e3e7f0), to(#f7f8fc));\n  background-image: linear-gradient(to top, #e3e7f0 0%, #f7f8fc 100%);\n  z-index: 10; }\n\n.container {\n  position: relative;\n  width: 100%;\n  height: 100vh;\n  background-image: -webkit-gradient(linear, left bottom, left top, from(#d8deec), to(#ffffff));\n  background-image: linear-gradient(to top, #d8deec 0%, #ffffff 100%);\n  overflow: hidden; }\n  .container::before {\n    content: '';\n    position: absolute;\n    top: -520px;\n    left: -180px;\n    width: 630px;\n    height: 630px;\n    border-radius: 50%;\n    background-image: -webkit-gradient(linear, left top, right top, from(#ff18be), to(#fe3032));\n    background-image: linear-gradient(to right, #ff18be 0%, #fe3032 100%); }\n  .container::after {\n    content: '';\n    position: absolute;\n    bottom: -250px;\n    right: -130px;\n    width: 450px;\n    height: 450px;\n    border-radius: 50%;\n    background-image: -webkit-gradient(linear, left bottom, left top, from(#21d4ff), to(#3151fe));\n    background-image: linear-gradient(to top, #21d4ff 0%, #3151fe 100%); }\n\n.nav {\n  position: absolute;\n  top: 20px;\n  right: 0;\n  z-index: 20; }\n  .nav__item {\n    display: block;\n    padding: 10px 60px 10px 25px;\n    margin-bottom: 10px;\n    border-radius: 10px;\n    color: #999a9e;\n    font-weight: 300;\n    background: -webkit-gradient(linear, left top, right top, from(#eef2f5), to(#fbfbfb));\n    background: linear-gradient(to right, #eef2f5 0%, #fbfbfb 100%);\n    -webkit-transition: all 1s ease;\n    transition: all 1s ease;\n    cursor: pointer;\n    opacity: 0;\n    -webkit-animation: fadeInLeft 1s forwards;\n            animation: fadeInLeft 1s forwards; }\n    .nav__item i {\n      margin-right: 10px;\n      color: #b2b3b7; }\n    .nav__item:hover {\n      -webkit-box-shadow: 5px 5px 10px rgba(0, 0, 0, 0.05);\n              box-shadow: 5px 5px 10px rgba(0, 0, 0, 0.05); }\n    .nav__item:nth-child(1) {\n      -webkit-animation-delay: .5s;\n              animation-delay: .5s; }\n    .nav__item:nth-child(2) {\n      -webkit-animation-delay: 1s;\n              animation-delay: 1s; }\n    .nav__item:nth-child(3) {\n      -webkit-animation-delay: 1.5s;\n              animation-delay: 1.5s; }\n    .nav__item:nth-child(4) {\n      -webkit-animation-delay: 2s;\n              animation-delay: 2s; }\n\n@-webkit-keyframes fadeInLeft {\n  from {\n    opacity: 0;\n    -webkit-transform: translate3d(-100%, 0, 0);\n    transform: translate3d(-100%, 0, 0); }\n  to {\n    opacity: 1;\n    -webkit-transform: translate3d(0, 0, 0);\n    transform: translate3d(0, 0, 0); } }\n\n.profile {\n  position: absolute;\n  left: 90px;\n  bottom: 100px;\n  color: #000000;\n  z-index: 20; }\n  .profile__name {\n    position: relative;\n    font-family: \"Dosis\", \"Source Sans Pro\", \"Helvetica Neue\", Arial, sans-serif;\n    letter-spacing: 2px;\n    font-size: 18px;\n    font-weight: normal;\n    cursor: pointer; }\n    .profile__name span {\n      font-weight: bold; }\n    .profile__name .popover {\n      display: none;\n      position: absolute;\n      bottom: 42px;\n      padding: 5px;\n      background-color: rgba(0, 0, 0, 0.85);\n      border-radius: 5px;\n      -webkit-box-shadow: 0 0 5px rgba(0, 0, 0, 0.4);\n              box-shadow: 0 0 5px rgba(0, 0, 0, 0.4);\n      z-index: 20; }\n      .profile__name .popover:before {\n        content: '';\n        display: block;\n        position: absolute;\n        left: 50%;\n        bottom: -7px;\n        margin-left: -7px;\n        border-top: 7px solid rgba(0, 0, 0, 0.85);\n        border-right: 7px solid transparent;\n        border-left: 7px solid transparent; }\n    .profile__name:hover .popover {\n      display: block;\n      -webkit-animation: fade-in .3s linear 1, move-up .3s linear 1;\n              animation: fade-in .3s linear 1, move-up .3s linear 1; }\n  .profile__work {\n    margin: 10px 0;\n    font-size: 32px;\n    font-weight: 300; }\n  .profile__social-links a {\n    display: inline-block;\n    margin-right: 10px;\n    color: #999a9e;\n    -webkit-transition: all 1s ease;\n    transition: all 1s ease; }\n    .profile__social-links a:hover {\n      color: #f32975; }\n\n@-webkit-keyframes fade-in {\n  from {\n    opacity: 0; }\n  to {\n    opacity: 1; } }\n\n@-webkit-keyframes move-up {\n  from {\n    bottom: 30px; }\n  to {\n    bottom: 42px; } }\n\n.footer {\n  margin: 20px 0;\n  color: #c4c4c5; }\n  .footer a {\n    display: inline-block;\n    color: #c4c4c5;\n    font-size: 12px;\n    -webkit-transition: all 1s ease;\n    transition: all 1s ease; }\n    .footer a:hover {\n      color: #8b8c90; }\n\n@media screen and (max-width: 320px) {\n  .container::before {\n    width: 350px;\n    height: 350px;\n    top: -255px;\n    left: -180px; }\n  .container::after {\n    width: 150px;\n    height: 150px;\n    bottom: -70px;\n    right: -60px; }\n  .nav__item {\n    padding: 10px 40px 10px 25px; }\n  .profile {\n    left: 20px; }\n    .profile__name {\n      font-size: 16px; }\n    .profile__work {\n      font-size: 30px; }\n  .footer {\n    display: none; } }\n\n@media screen and (max-width: 620px) and (min-width: 321px) {\n  .container::before {\n    width: 400px;\n    height: 400px;\n    top: -290px;\n    left: -170px; }\n  .container::after {\n    width: 200px;\n    height: 200px;\n    bottom: -100px;\n    right: -85px; }\n  .profile {\n    left: 30px; }\n  .footer {\n    display: none; } }\n","js":"\nvar reloadCSS = require('_css_loader');\nmodule.hot.dispose(reloadCSS);\nmodule.hot.accept(reloadCSS);"},"hash":"c124a7104316ea65ba9d96d3eadae3b8","cacheData":{"env":{}}}